arfs/__init__.py
arfs/association.py
arfs/benchmark.py
arfs/gbm.py
arfs/parallel.py
arfs/preprocessing.py
arfs/sampling.py
arfs/utils.py
arfs/dataset/data/boston_bunch.joblib
arfs/dataset/data/housing.zip
arfs/feature_selection/__init__.py
arfs/feature_selection/allrelevant.py
arfs/feature_selection/base.py
arfs/feature_selection/lasso.py
arfs/feature_selection/mrmr.py
arfs/feature_selection/summary.py
arfs/feature_selection/unsupervised.py
arfs/feature_selection/variable_importance.py
arfs-3.0.0.dist-info/licenses/LICENSE.md
arfs-3.0.0.dist-info/METADATA
arfs-3.0.0.dist-info/WHEEL
arfs-3.0.0.dist-info/top_level.txt
arfs-3.0.0.dist-info/RECORD
