Metadata-Version: 2.4
Name: arfs
Version: 3.0.0
Summary: All Relevant Feature Selection and Maximal Relevant minimal redundancy FS
Author-email: Thomas Bury <bury.thomas@gmail.com>
License: MIT
Project-URL: Documentation, https://github.com/ThomasBury/arfs
Project-URL: Source, https://github.com/ThomasBury/arfs
Project-URL: Tracker, https://github.com/ThomasBury/arfs/issues
Project-URL: Download, https://pypi.org/project/arfs/
Keywords: feature-selection,all-relevant,selection,MRmr
Classifier: Programming Language :: Python :: 3
Requires-Python: <3.13,>=3.9
License-File: LICENSE.md
Requires-Dist: lightgbm>=4.6.0
Requires-Dist: matplotlib>=3.9.4
Requires-Dist: numpy>=2.0.2
Requires-Dist: pandas>=2.2.3
Requires-Dist: scikit-learn>=1.6.1
Requires-Dist: scipy>=1.13.1
Requires-Dist: seaborn>=0.13.2
Requires-Dist: shap>=0.47.0
Requires-Dist: statsmodels>=0.14.4
Requires-Dist: tqdm>=4.67.1
Provides-Extra: docs
Requires-Dist: ipykernel; extra == "docs"
Requires-Dist: ipython_genutils; extra == "docs"
Requires-Dist: pandoc; extra == "docs"
Requires-Dist: sphinx; extra == "docs"
Requires-Dist: sphinxawesome-theme==5.0.0b5; extra == "docs"
Requires-Dist: nbsphinx==0.9.2; extra == "docs"
Requires-Dist: sphinx-autodoc-typehints<1.24.0; extra == "docs"
Requires-Dist: sphinx-copybutton==0.5.2; extra == "docs"
Requires-Dist: sphinx-tabs==3.4.1; extra == "docs"
Provides-Extra: test
Requires-Dist: pytest; extra == "test"
Requires-Dist: pytest-cov; extra == "test"
Dynamic: license-file
